core/__init__.py
core/config.py
core/file_scanner.py
core/merger.py
filters/__init__.py
filters/base.py
filters/glob.py
filters/ignore.py
generators/__init__.py
generators/base.py
generators/markdown.py
generators/text.py
kasu/__init__.py
kasu/cli.py
kasu-0.0.6.dist-info/licenses/LICENSE
sanitizers/__init__.py
sanitizers/sanitizer.py
utils/__init__.py
utils/format_utils.py
utils/language_map.py
utils/list.py
utils/statistics.py
utils/tree.py
kasu-0.0.6.dist-info/METADATA
kasu-0.0.6.dist-info/WHEEL
kasu-0.0.6.dist-info/entry_points.txt
kasu-0.0.6.dist-info/top_level.txt
kasu-0.0.6.dist-info/RECORD
