Metadata-Version: 2.4
Name: kasu
Version: 0.0.6
Summary: KASU: Kind of ASsemble Utility for merging and sanitizing text files in a directory
Author-email: "@remokasu" <0w0.ebi.kaitai@gmail.com>
License: MIT License
Project-URL: Homepage, https://github.com/remokasu/kasu
Project-URL: Repository, https://github.com/remokasu/kasu
Project-URL: Issues, https://github.com/remokasu/kasu/issues
Requires-Python: >=3.7
License-File: LICENSE
Requires-Dist: chardet>=5.0.0
Requires-Dist: pyyaml>=6.0
Requires-Dist: pathspec>=0.11.0
Provides-Extra: dev
Requires-Dist: pytest>=7.0.0; extra == "dev"
Requires-Dist: pytest-cov>=4.0.0; extra == "dev"
Requires-Dist: pytest-mock>=3.10.0; extra == "dev"
Dynamic: license-file
